README.md
setup.py
ep_feature_sdk_4pd/__init__.py
ep_feature_sdk_4pd/db_handler.py
ep_feature_sdk_4pd.egg-info/PKG-INFO
ep_feature_sdk_4pd.egg-info/SOURCES.txt
ep_feature_sdk_4pd.egg-info/dependency_links.txt
ep_feature_sdk_4pd.egg-info/requires.txt
ep_feature_sdk_4pd.egg-info/top_level.txt
tests/test_process_feature.py