Metadata-Version: 2.1
Name: ep-feature-sdk-4pd
Version: 1.0.0
Summary: 4paradigm Ep Feature Service SDK Library for Python
Home-page: https://gitlab.4pd.io/electricityproject/ep-feature-sdk
Author: 4paradigm Ep Feature SDK
Author-email: 
Keywords: 4pd_ep_feature
Platform: any
Classifier: Intended Audience :: Developers
Classifier: Programming Language :: Python
Classifier: Programming Language :: Python :: 3
Classifier: Programming Language :: Python :: 3.6
Classifier: Programming Language :: Python :: 3.7
Classifier: Programming Language :: Python :: 3.8
Classifier: Programming Language :: Python :: 3.9
Classifier: Programming Language :: Python :: 3.10
Classifier: Topic :: Software Development
Requires-Python: >=3.6
Requires-Dist: requests
